{
  "type": "issue",
  "reference": "BTE n.º 48, de 1998",
  "date": "1998-01-01",
  "url": "https://bte.gep.msess.gov.pt/completos/1998/bte48_1998.pdf",
  "root": {
    "type": "root",
    "children": [
      {
        "type": "chapter",
        "header": "CAPÍTULO VI diário de 630$, para vigorar de 1 de Janeiro a 31 de Dezembro de 1999, independentemente do número de",
        "text": "Retribuição do trabalho horas que preste de serviço em cada dia de trabalho. a Cláusula 49. -A 2, 3 e 4 — . . . . . . . . . . . . . . . . . . . . . . . . . . . . . . . . . . . . . Diuturnidades",
        "children": []
      },
      {
        "type": "chapter",
        "header": "ANEXO V 1 — Os trabalhadores abrangidos pelo presente CCT Tabelas salariais têm direito, por cada período de três anos de perma- o   nência na mesma categoria profissional ou escalão, e  Tabela n.   1 (*) na mesma empresa, a uma diuturnidade, até ao máximo  (a vigorar de 1 de Janeiro de 1998 a 31 de Dezembro de 1998)",
        "text": "de três. Grupos Tabela A Tabela B 2 — As diuturnidades previstas no número anterior têm o valor de 5740$ cada uma, para vigorarem de\n0 . . . . . . . . . . . . . . . . . . . . . . . . . . . . . . . . 112 800$00 102 850$00 1 de Janeiro a 31 de Dezembro de 1998, e de 5885$ 1 . . . . . . . . . . . . . . . . . . . . . . . . . . . . . . . . 102 100$00 91 100$00 cada uma, para vigorarem de 1 de Janeiro a 31 de 2 . . . . . . . . . . . . . . . . . . . . . . . . . . . . . . . . 94 600$00 85 800$00 Dezembro de 1999. 3 . . . . . . . . . . . . . . . . . . . . . . . . . . . . . . . . 91 200$00 82 200$00 a o Bol. Trab. Emp., 1. série, n. 48, 29/12/1998 2224 SINDEQ — Sindicato Democrático da Energia, Grupos Tabela A Tabela B Química e Indústrias Diversas. Lisboa, 1 de Outubro de 1998. — Pelo Secretariado, 4 . . . . . . . . . . . . . . . . . . . . . . . . . . . . . . . . 88 450$00 78 800$00\n5 . . . . . . . . . . . . . . . . . . . . . . . . . . . . . . . . 83 550$00 75 400$00 (Assinatura ilegível.)\n6 . . . . . . . . . . . . . . . . . . . . . . . . . . . . . . . . 78 700$00 70 500$00\n7 . . . . . . . . . . . . . . . . . . . . . . . . . . . . . . . . 71 500$00 64 800$00\n8 . . . . . . . . . . . . . . . . . . . . . . . . . . . . . . . . 66 600$00 60 000$00 Declaração\n9 . . . . . . . . . . . . . . . . . . . . . . . . . . . . . . . . 63 200$00 56 750$00\n10 . . . . . . . . . . . . . . . . . . . . . . . . . . . . . . . 60 000$00 54 500$00 A FETESE — Federação dos Sindicatos dos Traba-\n11 . . . . . . . . . . . . . . . . . . . . . . . . . . . . . . . 55 600$00 49 650$00 lhadores de Escritório e Serviços, por si e em repre- 12 . . . . . . . . . . . . . . . . . . . . . . . . . . . . . . . 51 650$00 46 150$00 sentação do sindicato seu filiado: 13 . . . . . . . . . . . . . . . . . . . . . . . . . . . . . . . 48 400$00 43 300$00 SITESE — Sindicato dos Trabalhadores de Escri- (*) Sem prejuízo da aplicação do salário mínimo nacional, quando as remunerações aqui previstas forem inferiores. tório, Comércio, Hotelaria e Serviços. o Tabela n. 2 (*) Lisboa, 8 de Outubro de 1998. — Pelo Secretariado: (a vigorar de 1 de Janeiro de 1999 a 31 de Dezembro de 1999) (Assinaturas ilegíveis.) Entrado em 20 de Novembro de 1998. Grupos Tabela A Tabela B Depositado em 18 de Dezembro de 1998, a fl. 166 o o o do livro n. 8, com o n. 391/98, nos termos do artigo 24. o 0 . . . . . . . . . . . . . . . . . . . . . . . . . . . . . . . . 115 650$00 105 450$00 do Decreto-Lei n. 519-C1/79, na sua redacção actual.\n1 . . . . . . . . . . . . . . . . . . . . . . . . . . . . . . . . 104 700$00 93 400$00\n2 . . . . . . . . . . . . . . . . . . . . . . . . . . . . . . . . 97 000$00 87 950$00\n3 . . . . . . . . . . . . . . . . . . . . . . . . . . . . . . . . 93 500$00 84 300$00\n4 . . . . . . . . . . . . . . . . . . . . . . . . . . . . . . . . 90 700$00 80 800$00\n5 . . . . . . . . . . . . . . . . . . . . . . . . . . . . . . . . 85 650$00 77 300$00\n6 . . . . . . . . . . . . . . . . . . . . . . . . . . . . . . . . 80 700$00 72 300$00\n7 . . . . . . . . . . . . . . . . . . . . . . . . . . . . . . . . 73 300$00 66 450$00\n8 . . . . . . . . . . . . . . . . . . . . . . . . . . . . . . . . 68 300$00 61 500$00\n9 . . . . . . . . . . . . . . . . . . . . . . . . . . . . . . . . 64 800$00 58 200$00\n10 . . . . . . . . . . . . . . . . . . . . . . . . . . . . . . . 61 500$00 55 900$00 CCT entre a ANIL — Assoc. Nacional dos Indus-\n11 . . . . . . . . . . . . . . . . . . . . . . . . . . . . . . . 57 000$00 50 900$00 triais de Lacticínios e várias cooperativas de pro-\n12 . . . . . . . . . . . . . . . . . . . . . . . . . . . . . . . 52 950$00 47 350$00 dutores de leite e a FSIABT — Feder. dos Sind. 13 . . . . . . . . . . . . . . . . . . . . . . . . . . . . . . . 49 650$00 44 400$00 dos Trabalhadores das Ind. de Alimentação, (*) Sem prejuízo da aplicação do salário mínimo nacional, quando as remunerações Bebidas e Tabaco e outros — Deliberação da aqui previstas forem inferiores. comissão paritária — Rectificação. Notas a o média mensal, por número, igual ou superior a de 22 de Novembro de 1998, encontra-se publicada a 30 000 exemplares, ou inferior, mas com uma tiragem deliberação da comissão paritária do CCT mencionado média mensal por trabalhador igual ou superior a em epígrafe, o qual enferma de inexactidão, impondo-se 1200 exemplares. a necessária rectificação. 2 — A tabela «B» aplica-se às restantes empresas. Assim, na parte final da deliberação, a p. 2163, onde 3 — A presente revisão produz efeitos a partir de 1 de se lê «Pelas Associações Sindicais: Manuel Lopes FurJaneiro de 1998. tado, José Maria da Costa Lapa, Fernando Manuel 4 — As matérias que constam do CCT agora revisto Fidalgo e Manuel Coelho Alves» deve ler-se «Pelas que não foram objecto de alterações continuam a vigorar Associações Sindicais: Manuel Lopes Furtado, José nos termos que o mesmo estabelece. Maria da Costa Lapa, Fernando Manuel Fidalgo e Manuel Coelho Alves. Lisboa, 1 de Outubro de 1998. Pela Associação da Imprensa Diária: Entrado em 30 de Outubro de 1998. Anselmo Alexandre Guimarães Sarsfield da Costa Freitas. Depositado em 9 de Novembro de 1998, a fl. 164 o o o Pela FETICEQ — Federação dos Trabalhadores das Indústrias Cerâmica, Vidreira, do livro n. 8, com o n. 375/98, nos termos do artigo 24. Extractiva, Energia e Química: o do Decreto-Lei n. 519-C1/79, na sua redacção actual.». José Carlos Moura Nunes. Pelo SITESC — Sindicato dos Trabalhadores de Escritório, Serviços e Comércio: (Assinatura ilegível.) Pela FETESE — Federação dos Sindicatos dos Trabalhadores de Escritório e Serviços: António Maria Teixeira de Matos Cordeiro. CCT entre a Assoc. Portuguesa dos Industriais de Declaração Curtumes e a FETICEQ — Feder. dos TrabalhaPara os devidos efeitos se declara que a FETI- dores das Ind. Cerâmica, Vidreira, Extractiva, CEQ — Federação dos Trabalhadores das Indústrias Energia e Química (produção e funções auxiliaCerâmica, Vidreira, Extractiva, Energia e Química res) — Alteração salarial e outra — Rectificação. representa as seguintes associações sindicais: SINDEGRAF — Sindicato Democrático dos Grá- Por ter sido publicado com inexactidão no Boletim a o ficos Papel e Afins; do Trabalho e Emprego, 1. série, n. 46, de 15 de Dezema o 2225 Bol. Trab. Emp., 1. série, n. 48, 29/12/1998 bro de 1998, o CCT mencionado em título, a seguir AE entre a CIMPOR — Ind. de Cimentos, S. A., e se procede à necessária rectificação. a FETESE — Feder. dos Sind. dos Trabalhadores Assim, na parte final do texto, a p. 2214, onde lê de Escritório e Serviços e outros — Rectificação. «Entrado em 20 de Novembro de 1998. Depositado em o n. 519-C1/79, na sua redacção actual.» deve ler-se AE mencionado em epígrafe, o qual enferma de ine- «Entrado em 20 de Novembro de 1998. Depositado em xactidão, impondo-se, por isso, a necessária correcção. o 3 de Dezembro de 1998, a fl. 166 do livro n. 8, com Assim, a p. 2205 da citada publicação, no nível 14 o o o n. 389/98, nos termos do artigo 24. do Decreto-Lei da tabela I, onde se lê «600 000$00» deve ler-se o n. 519-C1/79, na sua redacção actual.». «360 000$00». a o Bol. Trab. Emp., 1. série, n. 48, 29/12/1998 2226",
        "children": []
      }
    ]
  }
}