{
  "type": "issue",
  "reference": "BTE n.º 44, de 1998",
  "date": "1998-01-01",
  "url": "https://bte.gep.msess.gov.pt/completos/1998/bte44_1998.pdf",
  "root": {
    "type": "root",
    "children": [
      {
        "type": "chapter",
        "header": "ANEXO III o   Ajudante de fogueiro do 1.   ano   . . . . . . . . Servente de limpeza . . . . . . . . . . . . . . . . . . . Tabela salarial XIV   Praticante até 17 anos . . . . . . . . . . . . . . . . .   52 300$00  Níveis   Categorias profissionais   Remunerações",
        "text": "( a) Abono para falhas — 5900$. (b ) Sem prejuízo da aplicação do regime do salário mínimo nacional. Chefe de escritório . . . . . . . . . . . . . . . . . . . I 144 700$00 Director de serviços . . . . . . . . . . . . . . . . . . . Porto, 6 de Novembro de 1998. Chefe de departamento/divisão/serviços . . . Pela Associação Portuguesa dos Industriais de Curtumes: Contabilista . . . . . . . . . . . . . . . . . . . . . . . . . II 133 350$00 (Assinaturas ilegíveis.) Técnico de contas . . . . . . . . . . . . . . . . . . . . Tesoureiro . . . . . . . . . . . . . . . . . . . . . . . . . . Pela FEPCES — Federação Portuguesa dos Sindicatos do Comércio, Escritórios e Serviços: (Assinatura ilegível.) Chefe de secção . . . . . . . . . . . . . . . . . . . . . . Guarda-livros . . . . . . . . . . . . . . . . . . . . . . . . III 125 900$00 Chefe de vendas . . . . . . . . . . . . . . . . . . . . . . Declaração Programador . . . . . . . . . . . . . . . . . . . . . . . . Para todos os efeitos se declara que a FEPCES — Federação Portuguesa dos Sindicatos do Coleccionador — expositor . . . . . . . . . . . . Comércio, Escritórios e Serviços representa os seguintes Correspondente em línguas estrangeiras . . . sindicatos: IV Secretário de direcção . . . . . . . . . . . . . . . . . 116 200$00 Ajudante de guarda-livros . . . . . . . . . . . . . . Sindicato dos Trabalhadores do Comércio, Escri- Inspector de vendas . . . . . . . . . . . . . . . . . . . tórios e Serviços do Minho; Sindicato dos Trabalhadores do Comércio e EscriPrimeiro-escriturário . . . . . . . . . . . . . . . . . . tórios do Distrito de Castelo Branco; Caixa ( a ) . . . . . . . . . . . . . . . . . . . . . . . . . . . . Sindicato dos Trabalhadores do Comércio, Escri- Operador mecanográfico . . . . . . . . . . . . . . V 114 750$00 Vendedor . . . . . . . . . . . . . . . . . . . . . . . . . . . tórios e Serviços do Distrito de Coimbra; Primeiro-encarregado . . . . . . . . . . . . . . . . . Sindicato dos Profissionais de Escritório e ComérFogueiro-encarregado . . . . . . . . . . . . . . . . . cio do Distrito da Guarda; Sindicato dos Trabalhadores do Comércio, Escritórios e Serviços do Distrito de Leiria; Segundo-escriturário . . . . . . . . . . . . . . . . . . a Fogueiro de 1. . . . . . . . . . . . . . . . . . . . . . . . CESL — Sindicato dos Trabalhadores do ComérOperador de máquinas de contabilidade cio, Escritórios e Serviços do Distrito de Lisboa; VI Perfurador-verificador . . . . . . . . . . . . . . . . 98 150$00 CESNORTE — Sindicato dos Trabalhadores do Cobrador ( a ) . . . . . . . . . . . . . . . . . . . . . . . . Comércio, Escritórios e Serviços do Norte; Esteno-dacilógrafo em línguas estrangeiras Sindicato dos Trabalhadores do Comércio e Ser- Primeiro-caixeiro . . . . . . . . . . . . . . . . . . . . . viços do Distrito de Santarém; a o Bol. Trab. Emp., 1. série, n. 44, 29/11/1998 2168 a CESSUL — Sindicato dos Trabalhadores do Cláusula 34. Comécio, Escritórios e Serviços do Sul; Ajudas de custo Sindicato dos Trabalhadores de Escritório, Comércio e Serviços do Distrito de Viseu; 1 — Os trabalhadores que se desloquem em serviço Sindicato dos Empregados de Escritório, Caixeiros terão direito às seguintes ajudas de custo: e Serviços da Horta; a ) Almoço ou jantar — 1600$; SITAM — Sindicato dos Trabalhadores de Escri- b ) Dormida — 3700$; tório, Comércio e Serviços da Região Autónoma c ) Pequeno-almoço — 450$; da Madeira; d ) Diária completa — 5500$. Sindicato dos Trabalhadores de Escritório e Comércio de Angra do Heroísmo; a Cláusula 36. Sindicato dos Trabalhadores Aduaneiros em Despachantes e Empresas; Subsídios de Caixa Sindicato dos Trabalhadores de Serviços de Por- 1 — Os caixas e cobradores terão direito a um sub- taria, Vigilância, Limpeza, Domésticos e Profissídio mensal de quebras de 2250$. sões Similares e Actividades Diversas; SINDESCOM — Sindicato dos Profissionais de 2 — . . . . . . . . . . . . . . . . . . . . . . . . . . . . . . . . . . . . . . . . . . Escritório, Comércio, Indústria, Turismo, Serviços e Correlativos das Ilhas de São Miguel e 3 — . . . . . . . . . . . . . . . . . . . . . . . . . . . . . . . . . . . . . . . . . . Santa Maria. 4 — . . . . . . . . . . . . . . . . . . . . . . . . . . . . . . . . . . . . . . . . . . Pela Comissão Executiva da Direcção Nacional, (Assinatura ilegível.)",
        "children": []
      },
      {
        "type": "chapter",
        "header": "ANEXO III Entrado em 13 de Novembro de 1998. Tabela salarial o   Depositado em 16 de Novembro de 1998, a fl. n. 165",
        "text": "o o o do livro n. 8, com o n. 383/98, nos termos do artigo 24. o Nível Vencimento do Decreto-Lei n. 519-C1/79, na sua redacção actual.\nI . . . . . . . . . . . . . . . . . . . . . . . . . . . . . . . . . . . . . . . . . . . . . 88 400$00 II . . . . . . . . . . . . . . . . . . . . . . . . . . . . . . . . . . . . . . . . . . . . 84 350$00 III . . . . . . . . . . . . . . . . . . . . . . . . . . . . . . . . . . . . . . . . . . . 79 100$00 IV . . . . . . . . . . . . . . . . . . . . . . . . . . . . . . . . . . . . . . . . . . . 77 850$00\nV . . . . . . . . . . . . . . . . . . . . . . . . . . . . . . . . . . . . . . . . . . . . 71 250$00 VI . . . . . . . . . . . . . . . . . . . . . . . . . . . . . . . . . . . . . . . . . . . 68 000$00 VII . . . . . . . . . . . . . . . . . . . . . . . . . . . . . . . . . . . . . . . . . . 63 000$00 VIII . . . . . . . . . . . . . . . . . . . . . . . . . . . . . . . . . . . . . . . . . . 61 300$00 CCT entre a Assoc. Comercial do Dist. de Beja e IX . . . . . . . . . . . . . . . . . . . . . . . . . . . . . . . . . . . . . . . . . . . 59 500$00 o CESSUL — Sind. dos Trabalhadores do X . . . . . . . . . . . . . . . . . . . . . . . . . . . . . . . . . . . . . . . . . . . . 44 400$00 Comércio, Escritórios e Serviços do Sul e outro — Alteração salarial e outras. Beja, 30 de Setembro de 1998. Pela Associação Comercial do Distrito de Beja: a Cláusula 2. (Assinaturas ilegíveis.) Vigência e denúncia Pelo CESSUL — Sindicato dos Trabalhadores do Comércio, Escritórios e Serviços do Sul: 1 — . . . . . . . . . . . . . . . . . . . . . . . . . . . . . . . . . . . . . . . . . . (Assinaturas ilegíveis.) Pelo Sindicato dos Trabalhadores de Transportes Rodoviários do Sul: o 2 — Sem prejuízo do disposto no n. 1, a tabela sala- (Assinaturas ilegíveis.) rial produz efeitos a partir de 1 de Setembro de 1998. Entrado em 30 de Outubro de 1998. a Depositado em 16 de Novembro de 1998, a fl. 165 Cláusula 32. o o o do livro n. 8, com o n. 382/98, nos termos do artigo 24. o Diuturnidades do Decreto-Lei n. 519-C1/79, na sua redacção actual. 1 — Aos trabalhadores de categoria sem promoção automática será atribuída uma diuturnidade de 2650$ por cada três anos de antiguidade na categoria, até ao limite de cinco diuturnidades. a Cláusula 33. CCT entre a ANF — Assoc. Nacional das Farmácias e o Sind. Nacional dos Farmacêuticos — Alteração Subsídio de almoço salarial e outras 1 — Todos os trabalhadores abrangidos por este a a o a CCTV têm direito a um subsídio de almoço no valor As cláusulas 44. , 47. , n. 1, alínea c ), e 48. -A do de 410$ por cada dia de trabalho prestado. CCT celebrado entre a Associação Nacional das Fara o 2169 Bol. Trab. Emp., 1. série, n. 44, 29/11/1998 mácias e o Sindicato Nacional dos Farmacêuticos, publi- Acordo de adesão entre a OVIGER — Produção, de 15 de Janeiro de 1978, com as alterações que lhe vados, S. A., e o SETAA — Sind. da Agricultura, foram introduzidas e publicadas no Boletim do Trabalho Alimentação e Florestas ao ACT entre a empresa a os e Emprego, 1. série, n. 16, de 29 de Abril de 1986, P E C — P r o d u t o s P e c u á r i o s d e P o r t u - 4, de 29 de Janeiro de 1994, 29, de 8 de Agosto de gal — SGPS, S. A., e outras e o SETAA — Sind. 1996, e 44, de 20 de Novembro de 1997, passam a ter da Agricultura, Alimentação e Florestas (publia seguinte redacção: cado no Boletim do Trabalho e Emprego, a os 1. série, n. 37/97 e 38/98). a Cláusula 44. Tabela salarial A OVIGER — Produção, Transformação e Comércio de Carnes e Derivados, S. A., e o SETAA — Sindicato 1 — A remuneração mínima mensal dos trabalhado- da Agricultura, Alimentação e Florestas acordam entre res abrangidos pelo presente contrato é a seguinte: si na adesão ao ACT celebrado entre a PEC — Produtos Pecuários SGPS, S. A., e o SETAA — sindicato da AgriRemuneração cultura, Alimentação e Florestas, cuja última revisão Categoria mínima a o 1. série, n. 38, de 15 de Outubro de 1998. Director-técnico . . . . . . . . . . . . . . . . . . . . . . . . . . . 262 100$00 Farmacêutico-adjunto . . . . . . . . . . . . . . . . . . . . . . 243 300$00 Alcains, 28 de Outubro de 1998. o Farmacêutico do 3. ano . . . . . . . . . . . . . . . . . . . . 227 300$00 o Farmacêutico do 2. ano . . . . . . . . . . . . . . . . . . . . 203 300$00 Pela OVIGER — Produção, Transformação e Comércio de Carnes e Derivados, o S. A.: Farmacêutico do 1. ano . . . . . . . . . . . . . . . . . . . . 192 600$00 (Assinaturas ilegíveis.) 2 — As remunerações mínimas constantes do número Pelo SETAA — sindicato da Agricultura, Alimentação e Florestas: anterior produzem efeitos retroactivos a 1 de Janeiro Jorge Santos. de 1998. Entrado em 12 de Novembro de 1998. a Depositado em 18 de Novembro de 1998, a fl. 165 Cláusula 47. o o o do livro n. 8, com o n. 384/98, nos termos do artigo 24. Trabalho extraordinário o do Decreto-Lei n. 519-C1/79, na sua redacção actual. 1 — . . . . . . . . . . . . . . . . . . . . . . . . . . . . . . . . . . . . . . . . .\nc ) : Noites de sábado para domingo ou de dia útil para feriado — 18 100$; Noites de semana, de domingo para segunda-feira ou de dia feriado para dia CCT entre a Assoc. dos Comerciantes do Porto útil — 12 900$. e o SETN — Sind. dos Engenheiros Técnicos — Alteração salarial — Rectificação a Cláusula 48. -A de 29 de Outubro de 1998, encontra-se publicado o CCT 1 — Por cada dia completo de trabalho efectivo pres- mencionado em epígrafe, o qual enferma de inexactidão, tado os trabalhadores têm direito a um subsídio de refei- impondo-se, por isso, a necessária rectificação. ção no montante de 600$. Assim, na parte final do CCT, a p. 1998, onde se lê: 2 — O disposto no número anterior produz efeitos «Pelo SETN — Sindicato dos Engenheiros Técnicos: a partir de 1 de Janeiro de 1998. (Assinaturas ilegíveis.) » Lisboa, 28 de Setembro de 1998. Pela ANF — Associação Nacional das Farmácias: deve ler-se: (Assinaturas ilegíveis.) «Pelo SETN — Sindicato dos Engenheiros Técnicos: Pelo Sindicato Nacional dos Farmacêuticos: (Assinaturas ilegíveis.) (Assinaturas ilegíveis.) Entrado em 10 de Novembro de 1998. Entrado em 20 de Outubro de 1998. Depositado em 16 de Novembro de 1998, a fl. 165 Depositado em 22 de Outubro de 1998, a fl. 161 do o o o o o o do livro n. 8, com o n. 381/98, nos termos do artigo 24. livro n. 8, com o n. 355/98, nos termos do artigo 24. o o do Decreto-Lei n. 519-C1/79, na sua redacção actual. do Decreto-Lei n. 519-C1/79, na sua redacção actual.» a o Bol. Trab. Emp., 1. série, n. 44, 29/11/1998 2170 o a CCT entre a ANESUL — Assoc. dos Agentes de Assim, no n. 1 da cláusula 1. , onde se lê «O presente Navegação e Empresas Operadoras Portuárias contrato obriga, por um lado, todas as empresas repredo Sul e o Sind. dos Descarregadores de Mar sentadas pela ANESUL — Associação dos Agentes de e Terra do Dist. de Setúbal e outro — Recti- Navegação e Empresas Operadoras Portuárias do Sul ficação. e pela AOPS — Associação Marítima e Portuária do Sul e, por outro, os trabalhadores» deve ler-se «O prePor ter sido publicado com erro de escrita no Boletim sente contrato obriga, por um lado, todas as empresas a o do Trabalho e Emprego, 1. série, n. 37, de 8 de Outubro representadas pela ANESUL — Associação dos Agende 1998, o CCT mencionado em título, a seguir se pro- tes de Navegação e Empresas Operadoras Portuárias cede à necessária rectificação. do Sul e, por outro, os trabalhadores». a o 2171 Bol. Trab. Emp., 1. série, n. 44, 29/11/1998",
        "children": []
      }
    ]
  }
}